Workbook

Sheet README
A1: Kenya Fintech — Data Analyst Dashboard
A3: Purpose: Formula-driven analyst dashboard covering the four levels of analytics —
A4: Descriptive, Diagnostic, Predictive (summary), and Prescriptive KPIs.
A6: Sheet guide:
A7: Dashboard — Executive KPI scorecard + charts (Level 1: Descriptive)
A8: Diagnostic — Root-cause pivot tables (Level 2: Diagnostic)
A9: Prescriptive — Actionable watchlists (Level 4: Prescriptive)
A10: Data_Transactions — Raw transaction records (source for all formulas)
A11: Data_Loans — Raw loan records
A12: Data_Customers — Raw customer records
A13: Data_Fraud — Raw fraud event records
A15: All KPI and pivot cells use SUMIFS / COUNTIFS / AVERAGEIFS formulas referencing the
... A19: fraud events) — see original source workbook README tab for generation details.

Sheet Dashboard
B2: Kenya Fintech — Executive Dashboard
B3: Level 1: Descriptive Analytics — Portfolio Snapshot
B5: Active Customers | D5: =COUNTIF(Data_Customers!$M$2:$M$1001,"Active") -> 738
B6: Total Transactions | D6: =COUNTA(Data_Transactions!$A$2:$A$3016) -> 3015
B7: Transaction Success Rate | D7: =COUNTIF(Data_Transactions!$I$2:$I$3016,"Completed")/COUNTA(Data_Transactions!$A$2:$A$3016) -> 0.67495854
B8: Total Fee Revenue (KES) | D8: =SUM(Data_Fees!$D$2:$D$3016) -> 371094.03
B9: Loan Book Outstanding (KES) | D9: =SUMIFS(Data_Loans!$K$2:$K$501,Data_Loans!$J$2:$J$501,"Active")+SUMIFS(Data_Loans!$K$2:$K$501,Data_Loans!$J$2:$J$501,"Defaulted") -> 25030586
B10: Loan Default Rate | D10: =COUNTIF(Data_Loans!$J$2:$J$501,"Defaulted")/(COUNTIF(Data_Loans!$J$2:$J$501,"Defaulted")+COUNTIF(Data_Loans!$J$2:$J$501,"Paid")) -> 0.38022814
B11: Open Fraud Cases | D11: =COUNTIF(Data_Fraud!$F$2:$F$151,"New") -> 35
B14: Transactions by Status | E14: Channel Usage
B15: Completed | C15: =COUNTIF(Data_Transactions!$I$2:$I$3016,"Completed") -> 2035 | E15: Agent | F15: =COUNTIF(Data_Transactions!$F$2:$F$3016,"Agent") -> 782
B16: Failed | C16: =COUNTIF(Data_Transactions!$I$2:$I$3016,"Failed") -> 492 | E16: USSD | F16: =COUNTIF(Data_Transactions!$F$2:$F$3016,"USSD") -> 766
B17: Reversed | C17: =COUNTIF(Data_Transactions!$I$2:$I$3016,"Reversed") -> 488 | E17: Mobile | F17: =COUNTIF(Data_Transactions!$F$2:$F$3016,"Mobile") -> 753
E18: App | F18: =COUNTIF(Data_Transactions!$F$2:$F$3016,"App") -> 714
B20: Value by Transaction Type (KES) | E20: Loan Book by Status
B21: Bill Payment | C21: =SUMIFS(Data_Transactions!$G$2:$G$3016,Data_Transactions!$E$2:$E$3016,"Bill Payment") -> 3888387.3 | E21: Active | F21: =COUNTIF(Data_Loans!$J$2:$J$501,"Active") -> 164
B22: Merchant Payment | C22: =SUMIFS(Data_Transactions!$G$2:$G$3016,Data_Transactions!$E$2:$E$3016,"Merchant Payment") -> 3969092.3 | E22: Paid | F22: =COUNTIF(Data_Loans!$J$2:$J$501,"Paid") -> 163
B23: Payment | C23: =SUMIFS(Data_Transactions!$G$2:$G$3016,Data_Transactions!$E$2:$E$3016,"Payment") -> 4421961.5 | E23: Defaulted | F23: =COUNTIF(Data_Loans!$J$2:$J$501,"Defaulted") -> 100
B24: Transfer | C24: =SUMIFS(Data_Transactions!$G$2:$G$3016,Data_Transactions!$E$2:$E$3016,"Transfer") -> 4686509.1 | E24: Rejected | F24: =COUNTIF(Data_Loans!$J$2:$J$501,"Rejected") -> 73
B25: Withdrawal | C25: =SUMIFS(Data_Transactions!$G$2:$G$3016,Data_Transactions!$E$2:$E$3016,"Withdrawal") -> 3735044.5

Sheet Diagnostic
B2: Diagnostic Analytics — Root-Cause Views
B3: Level 2: Why is it happening?
B6: Channel | C6: Completed | D6: Failed | E6: Reversed | F6: Fail/Reversal Rate
B7: Agent | C7: =COUNTIFS(Data_Transactions!$F$2:$F$3016,"Agent",Data_Transactions!$I$2:$I$3016,"Completed") -> 536 | D7: =COUNTIFS(Data_Transactions!$F$2:$F$3016,"Agent",Data_Transactions!$I$2:$I$3016,"Failed") -> 131 | E7: =COUNTIFS(Data_Transactions!$F$2:$F$3016,"Agent",Data_Transactions!$I$2:$I$3016,"Reversed") -> 115 | F7: =(D7+E7)/(C7+D7+E7) -> 0.31457801
B8: USSD | C8: =COUNTIFS(Data_Transactions!$F$2:$F$3016,"USSD",Data_Transactions!$I$2:$I$3016,"Completed") -> 520 | D8: =COUNTIFS(Data_Transactions!$F$2:$F$3016,"USSD",Data_Transactions!$I$2:$I$3016,"Failed") -> 139 | E8: =COUNTIFS(Data_Transactions!$F$2:$F$3016,"USSD",Data_Transactions!$I$2:$I$3016,"Reversed") -> 107 | F8: =(D8+E8)/(C8+D8+E8) -> 0.32114883
B9: Mobile | C9: =COUNTIFS(Data_Transactions!$F$2:$F$3016,"Mobile",Data_Transactions!$I$2:$I$3016,"Completed") -> 496 | D9: =COUNTIFS(Data_Transactions!$F$2:$F$3016,"Mobile",Data_Transactions!$I$2:$I$3016,"Failed") -> 115 | E9: =COUNTIFS(Data_Transactions!$F$2:$F$3016,"Mobile",Data_Transactions!$I$2:$I$3016,"Reversed") -> 142 | F9: =(D9+E9)/(C9+D9+E9) -> 0.34130146
B10: App | C10: =COUNTIFS(Data_Transactions!$F$2:$F$3016,"App",Data_Transactions!$I$2:$I$3016,"Completed") -> 483 | D10: =COUNTIFS(Data_Transactions!$F$2:$F$3016,"App",Data_Transactions!$I$2:$I$3016,"Failed") -> 107 | E10: =COUNTIFS(Data_Transactions!$F$2:$F$3016,"App",Data_Transactions!$I$2:$I$3016,"Reversed") -> 124 | F10: =(D10+E10)/(C10+D10+E10) -> 0.32352941
B13: Loan Default Rate by Product
B14: Loan Product | C14: Total Decided | D14: Defaults | E14: Default Rate
B15: Business Loan | C15: =COUNTIFS(Data_Loans!$E$2:$E$501,"Business Loan",Data_Loans!$J$2:$J$501,"Paid")+COUNTIFS(Data_Loans!$E$2:$E$501,"Business Loan",Data_Loans!$J$2:$J$501,"Defaulted") -> 89 | D15: =COUNTIFS(Data_Loans!$E$2:$E$501,"Business Loan",Data_Loans!$J$2:$J$501,"Defaulted") -> 38 | E15: =D15/C15 -> 0.42696629
B16: Mobile Credit | C16: =COUNTIFS(Data_Loans!$E$2:$E$501,"Mobile Credit",Data_Loans!$J$2:$J$501,"Paid")+COUNTIFS(Data_Loans!$E$2:$E$501,"Mobile Credit",Data_Loans!$J$2:$J$501,"Defaulted") -> 86 | D16: =COUNTIFS(Data_Loans!$E$2:$E$501,"Mobile Credit",Data_Loans!$J$2:$J$501,"Defaulted") -> 30 | E16: =D16/C16 -> 0.34883721
B17: Salary Advance | C17: =COUNTIFS(Data_Loans!$E$2:$E$501,"Salary Advance",Data_Loans!$J$2:$J$501,"Paid")+COUNTIFS(Data_Loans!$E$2:$E$501,"Salary Advance",Data_Loans!$J$2:$J$501,"Defaulted") -> 88 | D17: =COUNTIFS(Data_Loans!$E$2:$E$501,"Salary Advance",Data_Loans!$J$2:$J$501,"Defaulted") -> 32 | E17: =D17/C17 -> 0.36363636
B20: Loan Default Rate by Customer Income Band
B21: Income Band | C21: Total Decided | D21: Defaults | E21: Default Rate
B22: 20K-30K | C22: =SUMPRODUCT((Data_Loans!$J$2:$J$501<>"")*((Data_Loans!$J$2:$J$501="Paid")+(Data_Loans!$J$2:$J$501="Defaulted"))*(IFERROR(VLOOKUP(Data_Loans!$B$2:$B$501,Data_Customers!$A$2:$J$1001,9,0),"")="20K-30K")) -> 0 | D22: =SUMPRODUCT((Data_Loans!$J$2:$J$501="Defaulted")*(IFERROR(VLOOKUP(Data_Loans!$B$2:$B$501,Data_Customers!$A$2:$J$1001,9,0),"")="20K-30K")) -> 0 | E22: =IFERROR(D22/C22,0) -> 0
B23: 30K-50K | C23: =SUMPRODUCT((Data_Loans!$J$2:$J$501<>"")*((Data_Loans!$J$2:$J$501="Paid")+(Data_Loans!$J$2:$J$501="Defaulted"))*(IFERROR(VLOOKUP(Data_Loans!$B$2:$B$501,Data_Customers!$A$2:$J$1001,9,0),"")="30K-50K")) -> 0 | D23: =SUMPRODUCT((Data_Loans!$J$2:$J$501="Defaulted")*(IFERROR(VLOOKUP(Data_Loans!$B$2:$B$501,Data_Customers!$A$2:$J$1001,9,0),"")="30K-50K")) -> 0 | E23: =IFERROR(D23/C23,0) -> 0
B24: 50K-100K | C24: =SUMPRODUCT((Data_Loans!$J$2:$J$501<>"")*((Data_Loans!$J$2:$J$501="Paid")+(Data_Loans!$J$2:$J$501="Defaulted"))*(IFERROR(VLOOKUP(Data_Loans!$B$2:$B$501,Data_Customers!$A$2:$J$1001,9,0),"")="50K-100K")) -> 0 | D24: =SUMPRODUCT((Data_Loans!$J$2:$J$501="Defaulted")*(IFERROR(VLOOKUP(Data_Loans!$B$2:$B$501,Data_Customers!$A$2:$J$1001,9,0),"")="50K-100K")) -> 0 | E24: =IFERROR(D24/C24,0) -> 0
B25: 100K-250K | C25: =SUMPRODUCT((Data_Loans!$J$2:$J$501<>"")*((Data_Loans!$J$2:$J$501="Paid")+(Data_Loans!$J$2:$J$501="Defaulted"))*(IFERROR(VLOOKUP(Data_Loans!$B$2:$B$501,Data_Customers!$A$2:$J$1001,9,0),"")="100K-250K")) -> 0 | D25: =SUMPRODUCT((Data_Loans!$J$2:$J$501="Defaulted")*(IFERROR(VLOOKUP(Data_Loans!$B$2:$B$501,Data_Customers!$A$2:$J$1001,9,0),"")="100K-250K")) -> 0 | E25: =IFERROR(D25/C25,0) -> 0
B26: 250K+ | C26: =SUMPRODUCT((Data_Loans!$J$2:$J$501<>"")*((Data_Loans!$J$2:$J$501="Paid")+(Data_Loans!$J$2:$J$501="Defaulted"))*(IFERROR(VLOOKUP(Data_Loans!$B$2:$B$501,Data_Customers!$A$2:$J$1001,9,0),"")="250K+")) -> 0 | D26: =SUMPRODUCT((Data_Loans!$J$2:$J$501="Defaulted")*(IFERROR(VLOOKUP(Data_Loans!$B$2:$B$501,Data_Customers!$A$2:$J$1001,9,0),"")="250K+")) -> 0 | E26: =IFERROR(D26/C26,0) -> 0

Sheet Prescriptive
B2: Prescriptive Analytics — Action Lists
B3: Level 4: What should we do next?
B5: Note: These are ranked watchlists best generated dynamically. Sort/filter the raw data sheets directly, or use the SQL prescriptive queries (see /sql/05_prescriptive_kpis.sql) for the collections and fraud-triage worklists — a static Excel snapshot below shows the top loan and fraud items as of the data extract date.
B8: Top 10 Overdue Active Loans (Collections Priority)
B9: Loan ID | C9: Customer ID | D9: Product | E9: Outstanding (KES) | F9: Days Past Due
B10: =INDEX(Data_Loans!$A$2:$A$501,MATCH(G10,Data_Loans!$M$2:$M$501,0)) -> LOAN455 | C10: =INDEX(Data_Loans!$B$2:$B$501,MATCH(G10,Data_Loans!$M$2:$M$501,0)) -> CUS656 | D10: =INDEX(Data_Loans!$E$2:$E$501,MATCH(G10,Data_Loans!$M$2:$M$501,0)) -> Business Loan | E10: =INDEX(Data_Loans!$K$2:$K$501,MATCH(G10,Data_Loans!$M$2:$M$501,0)) -> 129280.7 | F10: =INDEX(Data_Loans!$L$2:$L$501,MATCH(G10,Data_Loans!$M$2:$M$501,0)) -> 90 | G10: =LARGE(Data_Loans!$M$2:$M$501,1) -> 90.000449
B11: =INDEX(Data_Loans!$A$2:$A$501,MATCH(G11,Data_Loans!$M$2:$M$501,0)) -> LOAN443 | C11: =INDEX(Data_Loans!$B$2:$B$501,MATCH(G11,Data_Loans!$M$2:$M$501,0)) -> CUS167 | D11: =INDEX(Data_Loans!$E$2:$E$501,MATCH(G11,Data_Loans!$M$2:$M$501,0)) -> Mobile Credit | E11: =INDEX(Data_Loans!$K$2:$K$501,MATCH(G11,Data_Loans!$M$2:$M$501,0)) -> 62431.11 | F11: =INDEX(Data_Loans!$L$2:$L$501,MATCH(G11,Data_Loans!$M$2:$M$501,0)) -> 90 | G11: =LARGE(Data_Loans!$M$2:$M$501,2) -> 90.000437
B12: =INDEX(Data_Loans!$A$2:$A$501,MATCH(G12,Data_Loans!$M$2:$M$501,0)) -> LOAN426 | C12: =INDEX(Data_Loans!$B$2:$B$501,MATCH(G12,Data_Loans!$M$2:$M$501,0)) -> CUS147 | D12: =INDEX(Data_Loans!$E$2:$E$501,MATCH(G12,Data_Loans!$M$2:$M$501,0)) -> Salary Advance | E12: =INDEX(Data_Loans!$K$2:$K$501,MATCH(G12,Data_Loans!$M$2:$M$501,0)) -> 13206.11 | F12: =INDEX(Data_Loans!$L$2:$L$501,MATCH(G12,Data_Loans!$M$2:$M$501,0)) -> 90 | G12: =LARGE(Data_Loans!$M$2:$M$501,3) -> 90.00042
B13: =INDEX(Data_Loans!$A$2:$A$501,MATCH(G13,Data_Loans!$M$2:$M$501,0)) -> LOAN422 | C13: =INDEX(Data_Loans!$B$2:$B$501,MATCH(G13,Data_Loans!$M$2:$M$501,0)) -> CUS442 | D13: =INDEX(Data_Loans!$E$2:$E$501,MATCH(G13,Data_Loans!$M$2:$M$501,0)) -> Salary Advance | E13: =INDEX(Data_Loans!$K$2:$K$501,MATCH(G13,Data_Loans!$M$2:$M$501,0)) -> 18909.36 | F13: =INDEX(Data_Loans!$L$2:$L$501,MATCH(G13,Data_Loans!$M$2:$M$501,0)) -> 90 | G13: =LARGE(Data_Loans!$M$2:$M$501,4) -> 90.000416
B14: =INDEX(Data_Loans!$A$2:$A$501,MATCH(G14,Data_Loans!$M$2:$M$501,0)) -> LOAN399 | C14: =INDEX(Data_Loans!$B$2:$B$501,MATCH(G14,Data_Loans!$M$2:$M$501,0)) -> CUS392 | D14: =INDEX(Data_Loans!$E$2:$E$501,MATCH(G14,Data_Loans!$M$2:$M$501,0)) -> Business Loan | E14: =INDEX(Data_Loans!$K$2:$K$501,MATCH(G14,Data_Loans!$M$2:$M$501,0)) -> 3152.26 | F14: =INDEX(Data_Loans!$L$2:$L$501,MATCH(G14,Data_Loans!$M$2:$M$501,0)) -> 90 | G14: =LARGE(Data_Loans!$M$2:$M$501,5) -> 90.000393
B15: =INDEX(Data_Loans!$A$2:$A$501,MATCH(G15,Data_Loans!$M$2:$M$501,0)) -> LOAN393 | C15: =INDEX(Data_Loans!$B$2:$B$501,MATCH(G15,Data_Loans!$M$2:$M$501,0)) -> CUS706 | D15: =INDEX(Data_Loans!$E$2:$E$501,MATCH(G15,Data_Loans!$M$2:$M$501,0)) -> Salary Advance | E15: =INDEX(Data_Loans!$K$2:$K$501,MATCH(G15,Data_Loans!$M$2:$M$501,0)) -> 11482.44 | F15: =INDEX(Data_Loans!$L$2:$L$501,MATCH(G15,Data_Loans!$M$2:$M$501,0)) -> 90 | G15: =LARGE(Data_Loans!$M$2:$M$501,6) -> 90.000387
B16: =INDEX(Data_Loans!$A$2:$A$501,MATCH(G16,Data_Loans!$M$2:$M$501,0)) -> LOAN314 | C16: =INDEX(Data_Loans!$B$2:$B$501,MATCH(G16,Data_Loans!$M$2:$M$501,0)) -> CUS286 | D16: =INDEX(Data_Loans!$E$2:$E$501,MATCH(G16,Data_Loans!$M$2:$M$501,0)) -> Business Loan | E16: =INDEX(Data_Loans!$K$2:$K$501,MATCH(G16,Data_Loans!$M$2:$M$501,0)) -> 47258.85 | F16: =INDEX(Data_Loans!$L$2:$L$501,MATCH(G16,Data_Loans!$M$2:$M$501,0)) -> 90 | G16: =LARGE(Data_Loans!$M$2:$M$501,7) -> 90.000308
B17: =INDEX(Data_Loans!$A$2:$A$501,MATCH(G17,Data_Loans!$M$2:$M$501,0)) -> LOAN309 | C17: =INDEX(Data_Loans!$B$2:$B$501,MATCH(G17,Data_Loans!$M$2:$M$501,0)) -> CUS811 | D17: =INDEX(Data_Loans!$E$2:$E$501,MATCH(G17,Data_Loans!$M$2:$M$501,0)) -> Mobile Credit | E17: =INDEX(Data_Loans!$K$2:$K$501,MATCH(G17,Data_Loans!$M$2:$M$501,0)) -> 24776.7 | F17: =INDEX(Data_Loans!$L$2:$L$501,MATCH(G17,Data_Loans!$M$2:$M$501,0)) -> 90 | G17: =LARGE(Data_Loans!$M$2:$M$501,8) -> 90.000303
B18: =INDEX(Data_Loans!$A$2:$A$501,MATCH(G18,Data_Loans!$M$2:$M$501,0)) -> LOAN264 | C18: =INDEX(Data_Loans!$B$2:$B$501,MATCH(G18,Data_Loans!$M$2:$M$501,0)) -> CUS210 | D18: =INDEX(Data_Loans!$E$2:$E$501,MATCH(G18,Data_Loans!$M$2:$M$501,0)) -> Mobile Credit | E18: =INDEX(Data_Loans!$K$2:$K$501,MATCH(G18,Data_Loans!$M$2:$M$501,0)) -> 121603.11 | F18: =INDEX(Data_Loans!$L$2:$L$501,MATCH(G18,Data_Loans!$M$2:$M$501,0)) -> 90 | G18: =LARGE(Data_Loans!$M$2:$M$501,9) -> 90.000258
B19: =INDEX(Data_Loans!$A$2:$A$501,MATCH(G19,Data_Loans!$M$2:$M$501,0)) -> LOAN247 | C19: =INDEX(Data_Loans!$B$2:$B$501,MATCH(G19,Data_Loans!$M$2:$M$501,0)) -> CUS492 | D19: =INDEX(Data_Loans!$E$2:$E$501,MATCH(G19,Data_Loans!$M$2:$M$501,0)) -> Salary Advance | E19: =INDEX(Data_Loans!$K$2:$K$501,MATCH(G19,Data_Loans!$M$2:$M$501,0)) -> 25584.73 | F19: =INDEX(Data_Loans!$L$2:$L$501,MATCH(G19,Data_Loans!$M$2:$M$501,0)) -> 90 | G19: =LARGE(Data_Loans!$M$2:$M$501,10) -> 90.000241

Sheet Data_Transactions
A1: transaction_id | B1: account_id | C1: customer_id | D1: transaction_date | E1: transaction_type | F1: channel | G1: amount_kes | H1: fee_kes | I1: status | J1: reference_number | K1: recipient_type | L1: merchant_id | M1: agent_id
A2: TXN001 | B2: ACC001 | C2: CUS001 | D2: 45659.385 | E2: Payment | F2: Mobile | G2: 2500 | H2: 25 | I2: Completed | J2: REF001 | K2: Merchant | L2: MER018
A3: TXN002 | B3: ACC002 | C3: CUS002 | D3: 45659.472 | E3: Transfer | F3: Mobile | G3: 15000 | H3: 75 | I3: Completed | J3: REF002 | K3: Individual | L3: MER035
A4: TXN003 | B4: ACC003 | C4: CUS003 | D4: 45660.365 | E4: Bill Payment | F4: Mobile | G4: 3200 | H4: 20 | I4: Completed | J4: REF003 | K4: Utility | L4: MER052
A5: TXN004 | B5: ACC004 | C5: CUS004 | D5: 45660.646 | E5: Merchant Payment | F5: USSD | G5: 8500 | H5: 50 | I5: Completed | J5: REF004 | K5: Merchant | L5: MER069
A6: TXN005 | B6: ACC005 | C6: CUS005 | D6: 45661.715 | E6: Withdrawal | F6: Agent | G6: 5000 | H6: 60 | I6: Completed | J6: REF005 | K6: Individual | M6: AGT066
A7: TXN006 | B7: ACC006 | C7: CUS006 | D7: 45662.559 | E7: Payment | F7: Mobile | G7: 1200 | H7: 15 | I7: Completed | J7: REF006 | K7: Merchant | L7: MER103
A8: TXN007 | B8: ACC007 | C8: CUS007 | D8: 45663.42 | E8: Transfer | F8: Mobile | G8: 50000 | H8: 100 | I8: Completed | J8: REF007 | K8: Business | L8: MER120
A9: TXN008 | B9: ACC008 | C9: CUS008 | D9: 45664.778 | E9: Payment | F9: Mobile | G9: 750 | H9: 10 | I9: Completed | J9: REF008 | K9: Merchant | L9: MER137
A10: TXN009 | B10: ACC009 | C10: CUS009 | D10: 45665.51 | E10: Payment | F10: App | G10: 22000 | H10: 100 | I10: Completed | J10: REF009 | K10: Merchant | L10: MER004
A11: TXN010 | B11: ACC010 | C11: CUS010 | D11: 45666.618 | E11: Transfer | F11: Mobile | G11: 12000 | H11: 50 | I11: Completed | J11: REF010 | K11: Individual | L11: MER021
A12: TXN011 | B12: ACC001 | C12: CUS001 | D12: 45667.375 | E12: Payment | F12: App | G12: 4500 | H12: 35 | I12: Completed | J12: REF011 | K12: Merchant | L12: MER038
A13: TXN012 | B13: ACC002 | C13: CUS002 | D13: 45667.688 | E13: Withdrawal | F13: Agent | G13: 10000 | H13: 75 | I13: Failed | J13: REF012 | K13: Individual | M13: AGT057
A14: TXN013 | B14: ACC007 | C14: CUS007 | D14: 45668.49 | E14: Merchant Payment | F14: App | G14: 35000 | H14: 100 | I14: Completed | J14: REF013 | K14: Merchant | L14: MER072
A15: TXN014 | B15: ACC009 | C15: CUS009 | D15: 45669.542 | E15: Transfer | F15: Mobile | G15: 75000 | H15: 150 | I15: Completed | J15: REF014 | K15: Business | L15: MER089
A16: TXN015 | B16: ACC004 | C16: CUS004 | D16: 45670.434 | E16: Bill Payment | F16: USSD | G16: 4200 | H16: 25 | I16: Completed | J16: REF015 | K16: Utility | L16: MER106
A17: TXN0016 | B17: ACC372 | C17: CUS372 | D17: 45930.734 | E17: Transfer | F17: USSD | G17: 14101.36 | H17: 75.95 | I17: Completed | J17: REF0016 | K17: Merchant | L17: MER123
A18: TXN0017 | B18: ACC822 | C18: CUS822 | D18: 45867.54 | E18: Withdrawal | F18: Agent | G18: 8780.1 | H18: 27.96 | I18: Completed | J18: REF0017 | K18: Business | M18: AGT022
A19: TXN0018 | B19: ACC717 | C19: CUS717 | D19: 45579.588 | E19: Payment | F19: App | G19: 5593.9 | H19: 36.08 | I19: Completed | J19: REF0018 | K19: Business | L19: MER007
A20: TXN0019 | B20: ACC389 | C20: CUS389 | D20: 45780.534 | E20: Merchant Payment | F20: USSD | G20: 4807.82 | H20: 52.6 | I20: Completed | J20: REF0019 | K20: Merchant | L20: MER024
A21: TXN0020 | B21: ACC908 | C21: CUS908 | D21: 45670.383 | E21: Transfer | F21: Mobile | G21: 1644.52 | H21: 9.76 | I21: Reversed | J21: REF0020 | K21: Individual | L21: MER041
A22: TXN0021 | B22: ACC985 | C22: CUS985 | D22: 45941.721 | E22: Payment | F22: Agent | G22: 664.62 | H22: 6.64 | I22: Completed | J22: REF0021 | K22: Utility | M22: AGT074
A23: TXN0022 | B23: ACC872 | C23: CUS872 | D23: 45550.564 | E23: Merchant Payment | F23: USSD | G23: 1833.33 | H23: 20.46 | I23: Completed | J23: REF0022 | K23: Merchant | L23: MER075
A24: TXN0023 | B24: ACC665 | C24: CUS665 | D24: 45536.678 | E24: Merchant Payment | F24: Mobile | G24: 3447.82 | H24: 8.29 | I24: Completed | J24: REF0023 | K24: Merchant | L24: MER092
A25: TXN0024 | B25: ACC134 | C25: CUS134 | D25: 45931.324 | E25: Merchant Payment | F25: Agent | G25: 4823.26 | H25: 19.28 | I25: Completed | J25: REF0024 | K25: Merchant | M25: AGT013
A26: TXN0025 | B26: ACC712 | C26: CUS712 | D26: 45980.656 | E26: Merchant Payment | F26: Agent | G26: 2869.02 | H26: 20.44 | I26: Reversed | J26: REF0025 | K26: Utility | M26: AGT026
A27: TXN0026 | B27: ACC136 | C27: CUS136 | D27: 45646.649 | E27: Merchant Payment | F27: Mobile | G27: 1932.59 | H27: 5.48 | I27: Reversed | J27: REF0026 | K27: Utility | L27: MER143
A28: TXN0027 | B28: ACC883 | C28: CUS883 | D28: 45813.417 | E28: Payment | F28: Mobile | G28: 3112.72 | H28: 31.17 | I28: Completed | J28: REF0027 | K28: Merchant | L28: MER010
A29: TXN0028 | B29: ACC755 | C29: CUS755 | D29: 45641.381 | E29: Payment | F29: App | G29: 1692.91 | H29: 13.76 | I29: Completed | J29: REF0028 | K29: Merchant | L29: MER027
A30: TXN0029 | B30: ACC191 | C30: CUS191 | D30: 45385.375 | E30: Payment | F30: Agent | G30: 2791.25 | H30: 11.45 | I30: Completed | J30: REF0029 | K30: Individual | M30: AGT078
A31: TXN0030 | B31: ACC488 | C31: CUS488 | D31: 45494.943 | E31: Withdrawal | F31: Mobile | G31: 7837.57 | H31: 73.01 | I31: Completed | J31: REF0030 | K31: Individual | M31: AGT091
A32: TXN0031 | B32: ACC520 | C32: CUS520 | D32: 45298.383 | E32: Withdrawal | F32: App | G32: 12138.93 | H32: 130.88 | I32: Reversed | J32: REF0031 | K32: Merchant | M32: AGT004
A33: TXN0032 | B33: ACC720 | C33: CUS720 | D33: 45369.549 | E33: Bill Payment | F33: Agent | G33: 1860.01 | H33: 19.27 | I33: Failed | J33: REF0032 | K33: Utility | M33: AGT017
A34: TXN0033 | B34: ACC224 | C34: CUS224 | D34: 45728.661 | E34: Bill Payment | F34: USSD | G34: 2833.37 | H34: 5.86 | I34: Completed | J34: REF0033 | K34: Merchant | L34: MER112
A35: TXN0034 | B35: ACC064 | C35: CUS064 | D35: 45356.932 | E35: Merchant Payment | F35: Mobile | G35: 8686.78 | H35: 75.93 | I35: Reversed | J35: REF0034 | K35: Merchant | L35: MER129
A36: TXN0035 | B36: ACC327 | C36: CUS327 | D36: 45894.781 | E36: Bill Payment | F36: USSD | G36: 10565.35 | H36: 28.09 | I36: Completed | J36: REF0035 | K36: Utility | L36: MER146
A37: TXN0036 | B37: ACC761 | C37: CUS761 | D37: 45783.772 | E37: Transfer | F37: App | G37: 2057.56 | H37: 15.35 | I37: Failed | J37: REF0036 | K37: Individual | L37: MER013
A38: TXN0037 | B38: ACC044 | C38: CUS044 | D38: 45999.768 | E38: Merchant Payment | F38: Agent | G38: 3598.58 | H38: 40.43 | I38: Completed | J38: REF0037 | K38: Business | M38: AGT082
A39: TXN0038 | B39: ACC157 | C39: CUS157 | D39: 45437.81 | E39: Transfer | F39: Agent | G39: 8950.85 | H39: 95.8 | I39: Completed | J39: REF0038 | K39: Merchant | M39: AGT095
A40: TXN0039 | B40: ACC445 | C40: CUS445 | D40: 45969.506 | E40: Merchant Payment | F40: Agent | G40: 4892.05 | H40: 14.42 | I40: Completed | J40: REF0039 | K40: Utility | M40: AGT008
A41: TXN0040 | B41: ACC346 | C41: CUS346 | D41: 45494.313 | E41: Withdrawal | F41: USSD | G41: 3085.75 | H41: 35.65 | I41: Completed | J41: REF0040 | K41: Individual | M41: AGT021
A42: TXN0041 | B42: ACC499 | C42: CUS499 | D42: 45913.935 | E42: Payment | F42: USSD | G42: 1900.45 | H42: 13.06 | I42: Completed | J42: REF0041 | K42: Merchant | L42: MER098
A43: TXN0042 | B43: ACC976 | C43: CUS976 | D43: 45623.943 | E43: Transfer | F43: Agent | G43: 2508.54 | H43: 28.68 | I43: Completed | J43: REF0042 | K43: Merchant | M43: AGT047
A44: TXN0043 | B44: ACC980 | C44: CUS980 | D44: 45607.515 | E44: Payment | F44: App | G44: 8171.24 | H44: 51.4 | I44: Failed | J44: REF0043 | K44: Utility | L44: MER132
A45: TXN0044 | B45: ACC350 | C45: CUS350 | D45: 45674.474 | E45: Bill Payment | F45: Agent | G45: 4978.43 | H45: 10.84 | I45: Completed | J45: REF0044 | K45: Individual | M45: AGT073
A46: TXN0045 | B46: ACC968 | C46: CUS968 | D46: 45626.624 | E46: Merchant Payment | F46: USSD | G46: 10178.08 | H46: 113.56 | I46: Failed | J46: REF0045 | K46: Utility | L46: MER016
A47: TXN0046 | B47: ACC592 | C47: CUS592 | D47: 45631.581 | E47: Transfer | F47: App | G47: 1566.78 | H47: 13.05 | I47: Completed | J47: REF0046 | K47: Business | L47: MER033
A48: TXN0047 | B48: ACC577 | C48: CUS577 | D48: 45773.306 | E48: Withdrawal | F48: USSD | G48: 4108.41 | H48: 39.04 | I48: Completed | J48: REF0047 | K48: Business | M48: AGT012
A49: TXN0048 | B49: ACC474 | C49: CUS474 | D49: 45909.628 | E49: Bill Payment | F49: App | G49: 2726.12 | H49: 27.02 | I49: Completed | J49: REF0048 | K49: Merchant | L49: MER067
A50: TXN0049 | B50: ACC486 | C50: CUS486 | D50: 45544.611 | E50: Withdrawal | F50: App | G50: 1070.47 | H50: 8.78 | I50: Completed | J50: REF0049 | K50: Utility | M50: AGT038
A51: TXN0050 | B51: ACC497 | C51: CUS497 | D51: 45613.578 | E51: Withdrawal | F51: Mobile | G51: 7759.24 | H51: 87.19 | I51: Completed | J51: REF0050 | K51: Merchant | M51: AGT051
A52: TXN0051 | B52: ACC754 | C52: CUS754 | D52: 45491.677 | E52: Payment | F52: USSD | G52: 9550.22 | H52: 97.28 | I52: Completed | J52: REF0051 | K52: Individual | L52: MER118
A53: TXN0052 | B53: ACC148 | C53: CUS148 | D53: 45595.292 | E53: Merchant Payment | F53: App | G53: 12024.7 | H53: 33.51 | I53: Completed | J53: REF0052 | K53: Business | L53: MER135
A54: TXN0053 | B54: ACC569 | C54: CUS569 | D54: 45452.908 | E54: Bill Payment | F54: App | G54: 3662.08 | H54: 29.54 | I54: Failed | J54: REF0053 | K54: Individual | L54: MER002
A55: TXN0054 | B55: ACC331 | C55: CUS331 | D55: 45309.419 | E55: Bill Payment | F55: Agent | G55: 16481.42 | H55: 93.75 | I55: Failed | J55: REF0054 | K55: Merchant | M55: AGT003
A56: TXN0055 | B56: ACC644 | C56: CUS644 | D56: 45736.726 | E56: Bill Payment | F56: USSD | G56: 965.17 | H56: 9.27 | I56: Failed | J56: REF0055 | K56: Merchant | L56: MER036
A57: TXN0056 | B57: ACC905 | C57: CUS905 | D57: 45815.365 | E57: Payment | F57: App | G57: 6181.71 | H57: 16.31 | I57: Completed | J57: REF0056 | K57: Merchant | L57: MER053
A58: TXN0057 | B58: ACC536 | C58: CUS536 | D58: 45459.587 | E58: Merchant Payment | F58: Agent | G58: 2508.15 | H58: 23.85 | I58: Failed | J58: REF0057 | K58: Merchant | M58: AGT042
A59: TXN0058 | B59: ACC538 | C59: CUS538 | D59: 45718.822 | E59: Bill Payment | F59: App | G59: 10698.68 | H59: 33.73 | I59: Completed | J59: REF0058 | K59: Merchant | L59: MER087
A60: TXN0059 | B60: ACC661 | C60: CUS661 | D60: 45991.294 | E60: Payment | F60: App | G60: 9043.99 | H60: 61.38 | I60: Completed | J60: REF0059 | K60: Individual | L60: MER104
A61: TXN0060 | B61: ACC978 | C61: CUS978 | D61: 45432.722 | E61: Withdrawal | F61: USSD | G61: 2373.99 | H61: 14.14 | I61: Completed | J61: REF0060 | K61: Merchant | M61: AGT081
A62: TXN0061 | B62: ACC686 | C62: CUS686 | D62: 46005.858 | E62: Transfer | F62: Agent | G62: 1593.02 | H62: 5 | I62: Completed | J62: REF0061 | K62: Utility | M62: AGT094
A63: TXN0062 | B63: ACC719 | C63: CUS719 | D63: 45374.772 | E63: Withdrawal | F63: Mobile | G63: 9118.73 | H63: 37.64 | I63: Reversed | J63: REF0062 | K63: Utility | M63: AGT007
A64: TXN0063 | B64: ACC273 | C64: CUS273 | D64: 45861.772 | E64: Bill Payment | F64: USSD | G64: 1262.86 | H64: 12.05 | I64: Completed | J64: REF0063 | K64: Utility | L64: MER022
A65: TXN0064 | B65: ACC920 | C65: CUS920 | D65: 45558.797 | E65: Withdrawal | F65: Agent | G65: 6442.85 | H65: 41.59 | I65: Completed | J65: REF0064 | K65: Individual | M65: AGT033
A66: TXN0065 | B66: ACC116 | C66: CUS116 | D66: 45334.827 | E66: Bill Payment | F66: App | G66: 491.57 | H66: 5 | I66: Failed | J66: REF0065 | K66: Utility | L66: MER056
A67: TXN0066 | B67: ACC370 | C67: CUS370 | D67: 45766.362 | E67: Bill Payment | F67: App | G67: 6630.9 | H67: 71.9 | I67: Failed | J67: REF0066 | K67: Merchant | L67: MER073
A68: TXN0067 | B68: ACC318 | C68: CUS318 | D68: 45304.578 | E68: Merchant Payment | F68: USSD | G68: 1769.01 | H68: 12.38 | I68: Completed | J68: REF0067 | K68: Business | L68: MER090
A69: TXN0068 | B69: ACC617 | C69: CUS617 | D69: 45461.938 | E69: Transfer | F69: Mobile | G69: 4656.51 | H69: 55.26 | I69: Failed | J69: REF0068 | K69: Merchant | L69: MER107
A70: TXN0069 | B70: ACC906 | C70: CUS906 | D70: 45292.319 | E70: Payment | F70: Mobile | G70: 2842.78 | H70: 33.01 | I70: Completed | J70: REF0069 | K70: Individual | L70: MER124
A71: TXN0070 | B71: ACC662 | C71: CUS662 | D71: 45487.866 | E71: Payment | F71: USSD | G71: 3481.45 | H71: 33.79 | I71: Completed | J71: REF0070 | K71: Utility | L71: MER141
A72: TXN0071 | B72: ACC468 | C72: CUS468 | D72: 45501.457 | E72: Bill Payment | F72: USSD | G72: 2046.51 | H72: 18.31 | I72: Completed | J72: REF0071 | K72: Business | L72: MER008
A73: TXN0072 | B73: ACC065 | C73: CUS065 | D73: 46000.467 | E73: Merchant Payment | F73: App | G73: 808.62 | H73: 8.33 | I73: Completed | J73: REF0072 | K73: Merchant | L73: MER025
A74: TXN0073 | B74: ACC673 | C74: CUS673 | D74: 45356.656 | E74: Payment | F74: USSD | G74: 1959.65 | H74: 19.63 | I74: Completed | J74: REF0073 | K74: Individual | L74: MER042
A75: TXN0074 | B75: ACC707 | C75: CUS707 | D75: 45750.32 | E75: Withdrawal | F75: Agent | G75: 671.49 | H75: 7.1 | I75: Completed | J75: REF0074 | K75: Merchant | M75: AGT063
A76: TXN0075 | B76: ACC294 | C76: CUS294 | D76: 45664.401 | E76: Bill Payment | F76: USSD | G76: 1130.27 | H76: 8.42 | I76: Reversed | J76: REF0075 | K76: Individual | L76: MER076
A77: TXN0076 | B77: ACC329 | C77: CUS329 | D77: 45946.768 | E77: Bill Payment | F77: USSD | G77: 1579.74 | H77: 10.54 | I77: Completed | J77: REF0076 | K77: Business | L77: MER093
A78: TXN0077 | B78: ACC692 | C78: CUS692 | D78: 45847.849 | E78: Merchant Payment | F78: Agent | G78: 2462.74 | H78: 27.7 | I78: Failed | J78: REF0077 | K78: Individual | M78: AGT002
A79: TXN0078 | B79: ACC912 | C79: CUS912 | D79: 45335.731 | E79: Transfer | F79: App | G79: 1595.71 | H79: 13.29 | I79: Completed | J79: REF0078 | K79: Business | L79: MER127
A80: TXN0079 | B80: ACC084 | C80: CUS084 | D80: 45721.439 | E80: Bill Payment | F80: App | G80: 4708.4 | H80: 36.51 | I80: Reversed | J80: REF0079 | K80: Individual | L80: MER144
A81: TXN0080 | B81: ACC701 | C81: CUS701 | D81: 46018.73 | E81: Merchant Payment | F81: App | G81: 12432.05 | H81: 73.97 | I81: Failed | J81: REF0080 | K81: Utility | L81: MER011
A82: TXN0081 | B82: ACC768 | C82: CUS768 | D82: 45709.426 | E82: Transfer | F82: Mobile | G82: 6254.61 | H82: 64.69 | I82: Failed | J82: REF0081 | K82: Merchant | L82: MER028
A83: TXN0082 | B83: ACC508 | C83: CUS508 | D83: 45439.406 | E83: Transfer | F83: Mobile | G83: 11142.03 | H83: 67.53 | I83: Completed | J83: REF0082 | K83: Merchant | L83: MER045
A84: TXN0083 | B84: ACC017 | C84: CUS017 | D84: 45323.672 | E84: Payment | F84: Agent | G84: 5607.52 | H84: 36.59 | I84: Completed | J84: REF0083 | K84: Business | M84: AGT080
A85: TXN0084 | B85: ACC011 | C85: CUS011 | D85: 46006.681 | E85: Withdrawal | F85: Agent | G85: 3154.91 | H85: 19.83 | I85: Reversed | J85: REF0084 | K85: Merchant | M85: AGT093
A86: TXN0085 | B86: ACC696 | C86: CUS696 | D86: 45795.355 | E86: Merchant Payment | F86: Mobile | G86: 2923.86 | H86: 26.33 | I86: Completed | J86: REF0085 | K86: Utility | L86: MER096
A87: TXN0086 | B87: ACC972 | C87: CUS972 | D87: 45993.917 | E87: Payment | F87: Mobile | G87: 6546.35 | H87: 29.6 | I87: Completed | J87: REF0086 | K87: Merchant | L87: MER113
A88: TXN0087 | B88: ACC466 | C88: CUS466 | D88: 45680.719 | E88: Withdrawal | F88: Agent | G88: 5624.63 | H88: 29.41 | I88: Completed | J88: REF0087 | K88: Business | M88: AGT032
A89: TXN0088 | B89: ACC098 | C89: CUS098 | D89: 45302.484 | E89: Merchant Payment | F89: USSD | G89: 15442.6 | H89: 108.42 | I89: Reversed | J89: REF0088 | K89: Business | L89: MER147
A90: TXN0089 | B90: ACC821 | C90: CUS821 | D90: 45840.344 | E90: Merchant Payment | F90: USSD | G90: 6548.24 | H90: 45.25 | I90: Completed | J90: REF0089 | K90: Merchant | L90: MER014
A91: TXN0090 | B91: ACC298 | C91: CUS298 | D91: 45907.727 | E91: Transfer | F91: Agent | G91: 1822.11 | H91: 18.9 | I91: Completed | J91: REF0090 | K91: Individual | M91: AGT071
A92: TXN0091 | B92: ACC006 | C92: CUS006 | D92: 45688.534 | E92: Withdrawal | F92: Agent | G92: 2971.68 | H92: 12.58 | I92: Completed | J92: REF0091 | K92: Business | M92: AGT084
A93: TXN0092 | B93: ACC828 | C93: CUS828 | D93: 46009.421 | E93: Withdrawal | F93: Mobile | G93: 2073.06 | H93: 24.44 | I93: Completed | J93: REF0092 | K93: Business | M93: AGT097
A94: TXN0093 | B94: ACC376 | C94: CUS376 | D94: 46007.834 | E94: Payment | F94: USSD | G94: 2452.94 | H94: 15.17 | I94: Completed | J94: REF0093 | K94: Business | L94: MER082
A95: TXN0094 | B95: ACC069 | C95: CUS069 | D95: 45358.386 | E95: Withdrawal | F95: App | G95: 27802.77 | H95: 187.56 | I95: Completed | J95: REF0094 | K95: Merchant | M95: AGT023
A96: TXN0095 | B96: ACC025 | C96: CUS025 | D96: 45457.4 | E96: Withdrawal | F96: USSD | G96: 2061.65 | H96: 17.73 | I96: Failed | J96: REF0095 | K96: Utility | M96: AGT036
A97: TXN0096 | B97: ACC490 | C97: CUS490 | D97: 45360.526 | E97: Transfer | F97: USSD | G97: 2869.94 | H97: 12.41 | I97: Completed | J97: REF0096 | K97: Business | L97: MER133
A98: TXN0097 | B98: ACC012 | C98: CUS012 | D98: 45672.356 | E98: Withdrawal | F98: Mobile | G98: 7023.58 | H98: 60.82 | I98: Completed | J98: REF0097 | K98: Individual | M98: AGT062
A99: TXN0098 | B99: ACC328 | C99: CUS328 | D99: 45541.952 | E99: Transfer | F99: Mobile | G99: 932.03 | H99: 6.32 | I99: Completed | J99: REF0098 | K99: Business | L99: MER017
A100: TXN0099 | B100: ACC567 | C100: CUS567 | D100: 45940.381 | E100: Payment | F100: Agent | G100: 30223.05 | H100: 104.39 | I100: Failed | J100: REF0099 | K100: Merchant | M100: AGT088
...

Sheet Data_Loans
A1: loan_id | B1: customer_id | C1: application_date | D1: approval_date | E1: loan_product | F1: requested_amount | G1: approved_amount | H1: interest_rate | I1: term_days | J1: loan_status | K1: outstanding_balance | L1: days_past_due | M1: dpd_rank_key
A2: LOAN008 | B2: CUS698 | C2: 45753 | D2: 45755 | E2: Mobile Credit | F2: 139348.46 | G2: 112379.63 | H2: 17.034 | I2: 30 | J2: Paid | K2: 0 | L2: 0 | M2: =IF(J2="Active",L2+(ROW()/1000000),"")
A3: LOAN009 | B3: CUS673 | C3: 45488 | D3: 45492 | E3: Mobile Credit | F3: 397699.36 | G3: 392476.19 | H3: 13.228 | I3: 30 | J3: Active | K3: 229830.58 | L3: 1 | M3: =IF(J3="Active",L3+(ROW()/1000000),"") -> 1.000003
A4: LOAN010 | B4: CUS883 | C4: 45704 | D4: 45707 | E4: Business Loan | F4: 414918.05 | G4: 341170.45 | H4: 13.114 | I4: 90 | J4: Paid | K4: 0 | L4: 0 | M4: =IF(J4="Active",L4+(ROW()/1000000),"")
A5: LOAN011 | B5: CUS034 | C5: 45450 | D5: 45452 | E5: Salary Advance | F5: 284697.31 | G5: 216103.07 | H5: 10.509 | I5: 120 | J5: Defaulted | K5: 73422.53 | L5: 15 | M5: =IF(J5="Active",L5+(ROW()/1000000),"")
A6: LOAN012 | B6: CUS990 | C6: 45424 | E6: Mobile Credit | F6: 12056.42 | G6: 0 | H6: 9.618 | I6: 120 | J6: Rejected | K6: 0 | L6: 0 | M6: =IF(J6="Active",L6+(ROW()/1000000),"")
A7: LOAN013 | B7: CUS328 | C7: 45721 | D7: 45721 | E7: Salary Advance | F7: 495392.38 | G7: 282218.42 | H7: 12.981 | I7: 30 | J7: Active | K7: 154932.61 | L7: 10 | M7: =IF(J7="Active",L7+(ROW()/1000000),"") -> 10.000007
A8: LOAN014 | B8: CUS884 | C8: 45830 | E8: Mobile Credit | F8: 258171.49 | G8: 0 | H8: 14.689 | I8: 30 | J8: Rejected | K8: 0 | L8: 0 | M8: =IF(J8="Active",L8+(ROW()/1000000),"")
A9: LOAN015 | B9: CUS001 | C9: 45632 | D9: 45635 | E9: Salary Advance | F9: 230751.99 | G9: 142881.48 | H9: 8.763 | I9: 60 | J9: Active | K9: 118411.61 | L9: 30 | M9: =IF(J9="Active",L9+(ROW()/1000000),"") -> 30.000009
A10: LOAN016 | B10: CUS053 | C10: 45487 | D10: 45491 | E10: Salary Advance | F10: 229880.17 | G10: 132787.15 | H10: 15.117 | I10: 60 | J10: Active | K10: 14111.16 | L10: 15 | M10: =IF(J10="Active",L10+(ROW()/1000000),"") -> 15.00001
A11: LOAN017 | B11: CUS210 | C11: 46016 | E11: Salary Advance | F11: 236351.63 | G11: 0 | H11: 11.307 | I11: 30 | J11: Rejected | K11: 0 | L11: 0 | M11: =IF(J11="Active",L11+(ROW()/1000000),"")
A12: LOAN018 | B12: CUS376 | C12: 45567 | D12: 45567 | E12: Mobile Credit | F12: 177456.52 | G12: 175689.78 | H12: 11.899 | I12: 60 | J12: Active | K12: 163037.51 | L12: 60 | M12: =IF(J12="Active",L12+(ROW()/1000000),"") -> 60.000012
A13: LOAN019 | B13: CUS466 | C13: 45429 | E13: Salary Advance | F13: 333260.89 | G13: 0 | H13: 13.538 | I13: 60 | J13: Rejected | K13: 0 | L13: 0 | M13: =IF(J13="Active",L13+(ROW()/1000000),"")
A14: LOAN020 | B14: CUS679 | C14: 45864 | D14: 45865 | E14: Business Loan | F14: 112246.72 | G14: 88907.48 | H14: 13.421 | I14: 120 | J14: Paid | K14: 0 | L14: 0 | M14: =IF(J14="Active",L14+(ROW()/1000000),"")
A15: LOAN021 | B15: CUS206 | C15: 45864 | E15: Salary Advance | F15: 386822.5 | G15: 0 | H15: 16.02 | I15: 120 | J15: Rejected | K15: 0 | L15: 0 | M15: =IF(J15="Active",L15+(ROW()/1000000),"")
A16: LOAN022 | B16: CUS661 | C16: 45962 | D16: 45962 | E16: Mobile Credit | F16: 309803.99 | G16: 219346.29 | H16: 13.703 | I16: 60 | J16: Paid | K16: 0 | L16: 0 | M16: =IF(J16="Active",L16+(ROW()/1000000),"")
A17: LOAN023 | B17: CUS963 | C17: 45537 | D17: 45539 | E17: Business Loan | F17: 184805.11 | G17: 145259.23 | H17: 16.298 | I17: 60 | J17: Paid | K17: 0 | L17: 0 | M17: =IF(J17="Active",L17+(ROW()/1000000),"")
A18: LOAN024 | B18: CUS914 | C18: 45819 | D18: 45820 | E18: Mobile Credit | F18: 114427.43 | G18: 83532.14 | H18: 16.762 | I18: 30 | J18: Defaulted | K18: 52865.44 | L18: 90 | M18: =IF(J18="Active",L18+(ROW()/1000000),"")
A19: LOAN025 | B19: CUS679 | C19: 45906 | D19: 45910 | E19: Mobile Credit | F19: 178321.65 | G19: 175113.89 | H19: 14.68 | I19: 60 | J19: Active | K19: 85705.07 | L19: 3 | M19: =IF(J19="Active",L19+(ROW()/1000000),"") -> 3.000019
A20: LOAN026 | B20: CUS602 | C20: 45711 | D20: 45716 | E20: Business Loan | F20: 139577.58 | G20: 113523.18 | H20: 7.709 | I20: 120 | J20: Active | K20: 83121.39 | L20: 90 | M20: =IF(J20="Active",L20+(ROW()/1000000),"") -> 90.00002
A21: LOAN027 | B21: CUS580 | C21: 45627 | D21: 45628 | E21: Salary Advance | F21: 331027.28 | G21: 279200.73 | H21: 14.505 | I21: 30 | J21: Defaulted | K21: 130604.9 | L21: 60 | M21: =IF(J21="Active",L21+(ROW()/1000000),"")
A22: LOAN028 | B22: CUS282 | C22: 45628 | D22: 45628 | E22: Salary Advance | F22: 461458.18 | G22: 270596.65 | H22: 17.476 | I22: 30 | J22: Paid | K22: 0 | L22: 0 | M22: =IF(J22="Active",L22+(ROW()/1000000),"")
A23: LOAN029 | B23: CUS485 | C23: 45933 | D23: 45937 | E23: Business Loan | F23: 259094.93 | G23: 181815.77 | H23: 13.456 | I23: 30 | J23: Active | K23: 58320.39 | L23: 30 | M23: =IF(J23="Active",L23+(ROW()/1000000),"") -> 30.000023
A24: LOAN030 | B24: CUS862 | C24: 45337 | E24: Business Loan | F24: 435031.25 | G24: 0 | H24: 9.022 | I24: 180 | J24: Rejected | K24: 0 | L24: 0 | M24: =IF(J24="Active",L24+(ROW()/1000000),"")
A25: LOAN031 | B25: CUS994 | C25: 45699 | D25: 45702 | E25: Salary Advance | F25: 368834.49 | G25: 342326.73 | H25: 9.039 | I25: 30 | J25: Paid | K25: 0 | L25: 0 | M25: =IF(J25="Active",L25+(ROW()/1000000),"")
A26: LOAN032 | B26: CUS849 | C26: 45349 | E26: Mobile Credit | F26: 320678.63 | G26: 0 | H26: 10.91 | I26: 30 | J26: Rejected | K26: 0 | L26: 0 | M26: =IF(J26="Active",L26+(ROW()/1000000),"")
A27: LOAN033 | B27: CUS083 | C27: 45875 | D27: 45880 | E27: Salary Advance | F27: 146186.18 | G27: 94238.13 | H27: 17.938 | I27: 120 | J27: Paid | K27: 0 | L27: 0 | M27: =IF(J27="Active",L27+(ROW()/1000000),"")
A28: LOAN034 | B28: CUS330 | C28: 45994 | D28: 45996 | E28: Salary Advance | F28: 330509.93 | G28: 273532.81 | H28: 11.638 | I28: 30 | J28: Active | K28: 98323.85 | L28: 10 | M28: =IF(J28="Active",L28+(ROW()/1000000),"") -> 10.000028
A29: LOAN035 | B29: CUS720 | C29: 45996 | E29: Salary Advance | F29: 137924.88 | G29: 0 | H29: 15.018 | I29: 30 | J29: Rejected | K29: 0 | L29: 0 | M29: =IF(J29="Active",L29+(ROW()/1000000),"")
A30: LOAN036 | B30: CUS107 | C30: 45639 | D30: 45640 | E30: Business Loan | F30: 328389.34 | G30: 197049.63 | H30: 14.741 | I30: 90 | J30: Defaulted | K30: 77275.42 | L30: 1 | M30: =IF(J30="Active",L30+(ROW()/1000000),"")
A31: LOAN037 | B31: CUS636 | C31: 45953 | D31: 45953 | E31: Mobile Credit | F31: 146294.4 | G31: 112291.68 | H31: 13.294 | I31: 30 | J31: Defaulted | K31: 6086.42 | L31: 10 | M31: =IF(J31="Active",L31+(ROW()/1000000),"")
A32: LOAN038 | B32: CUS403 | C32: 45958 | D32: 45960 | E32: Business Loan | F32: 452552.99 | G32: 311682 | H32: 7.557 | I32: 90 | J32: Paid | K32: 0 | L32: 0 | M32: =IF(J32="Active",L32+(ROW()/1000000),"")
A33: LOAN039 | B33: CUS829 | C33: 45776 | D33: 45778 | E33: Business Loan | F33: 244872.54 | G33: 152237.51 | H33: 12.039 | I33: 60 | J33: Defaulted | K33: 80593.37 | L33: 30 | M33: =IF(J33="Active",L33+(ROW()/1000000),"")
A34: LOAN040 | B34: CUS976 | C34: 45347 | D34: 45348 | E34: Mobile Credit | F34: 268055.76 | G34: 187635.08 | H34: 17.392 | I34: 30 | J34: Defaulted | K34: 122418.16 | L34: 90 | M34: =IF(J34="Active",L34+(ROW()/1000000),"")
A35: LOAN041 | B35: CUS880 | C35: 45982 | D35: 45985 | E35: Business Loan | F35: 23292.01 | G35: 20051.09 | H35: 13.903 | I35: 30 | J35: Active | K35: 5511.27 | L35: 30 | M35: =IF(J35="Active",L35+(ROW()/1000000),"") -> 30.000035
A36: LOAN042 | B36: CUS518 | C36: 45306 | D36: 45311 | E36: Mobile Credit | F36: 445241.57 | G36: 271854.09 | H36: 8.726 | I36: 30 | J36: Paid | K36: 0 | L36: 0 | M36: =IF(J36="Active",L36+(ROW()/1000000),"")
A37: LOAN043 | B37: CUS324 | C37: 45869 | D37: 45870 | E37: Business Loan | F37: 438438.12 | G37: 331244.1 | H37: 17.919 | I37: 60 | J37: Paid | K37: 0 | L37: 0 | M37: =IF(J37="Active",L37+(ROW()/1000000),"")
A38: LOAN044 | B38: CUS954 | C38: 45805 | D38: 45807 | E38: Salary Advance | F38: 192182.42 | G38: 188511.24 | H38: 10.93 | I38: 60 | J38: Paid | K38: 0 | L38: 0 | M38: =IF(J38="Active",L38+(ROW()/1000000),"")
A39: LOAN045 | B39: CUS340 | C39: 45813 | D39: 45817 | E39: Business Loan | F39: 280937.14 | G39: 273443.88 | H39: 7.269 | I39: 120 | J39: Paid | K39: 0 | L39: 0 | M39: =IF(J39="Active",L39+(ROW()/1000000),"")
A40: LOAN046 | B40: CUS781 | C40: 45685 | D40: 45689 | E40: Mobile Credit | F40: 492951.87 | G40: 382251.53 | H40: 14.236 | I40: 90 | J40: Paid | K40: 0 | L40: 0 | M40: =IF(J40="Active",L40+(ROW()/1000000),"")
A41: LOAN047 | B41: CUS896 | C41: 45814 | D41: 45814 | E41: Mobile Credit | F41: 60225.55 | G41: 34342.6 | H41: 10.777 | I41: 90 | J41: Paid | K41: 0 | L41: 0 | M41: =IF(J41="Active",L41+(ROW()/1000000),"")
... A44: LOAN050 | B44: CUS838 | C44: 45413 | D44: 45415 | E44: Mobile Credit | F44: 351079.12 | G44: 251844.82 | H44: 15.417 | I44: 120 | J44: Defaulted | K44: 163629.27 | L44: 15 | M44: =IF(J44="Active",L44+(ROW()/1000000),"")
A45: LOAN051 | B45: CUS042 | C45: 45729 | E45: Salary Advance | F45: 455208.89 | G45: 0 | H45: 8.165 | I45: 30 | J45: Rejected | K45: 0 | L45: 0 | M45: =IF(J45="Active",L45+(ROW()/1000000),"")
A46: LOAN052 | B46: CUS536 | C46: 45398 | E46: Mobile Credit | F46: 199981.25 | G46: 0 | H46: 9.176 | I46: 120 | J46: Rejected | K46: 0 | L46: 0 | M46: =IF(J46="Active",L46+(ROW()/1000000),"")
A47: LOAN053 | B47: CUS877 | C47: 45664 | D47: 45666 | E47: Salary Advance | F47: 310336.03 | G47: 216168.14 | H47: 17.331 | I47: 60 | J47: Defaulted | K47: 42623.78 | L47: 90 | M47: =IF(J47="Active",L47+(ROW()/1000000),"")
A48: LOAN054 | B48: CUS253 | C48: 45955 | D48: 45959 | E48: Salary Advance | F48: 147961.42 | G48: 122393.6 | H48: 7.958 | I48: 180 | J48: Active | K48: 56819.78 | L48: 30 | M48: =IF(J48="Active",L48+(ROW()/1000000),"") -> 30.000048
A49: LOAN055 | B49: CUS006 | C49: 45402 | D49: 45405 | E49: Business Loan | F49: 348304.1 | G49: 260764.47 | H49: 7.568 | I49: 90 | J49: Defaulted | K49: 82156.68 | L49: 3 | M49: =IF(J49="Active",L49+(ROW()/1000000),"")
A50: LOAN056 | B50: CUS559 | C50: 45930 | D50: 45934 | E50: Business Loan | F50: 433703.84 | G50: 339978.44 | H50: 9.457 | I50: 120 | J50: Active | K50: 64502.54 | L50: 0 | M50: =IF(J50="Active",L50+(ROW()/1000000),"") -> 5e-05
A51: LOAN057 | B51: CUS588 | C51: 45569 | D51: 45574 | E51: Business Loan | F51: 130182.31 | G51: 107010.6 | H51: 15.531 | I51: 120 | J51: Paid | K51: 0 | L51: 0 | M51: =IF(J51="Active",L51+(ROW()/1000000),"")
A52: LOAN058 | B52: CUS714 | C52: 45821 | E52: Salary Advance | F52: 293239.97 | G52: 0 | H52: 12.562 | I52: 30 | J52: Rejected | K52: 0 | L52: 0 | M52: =IF(J52="Active",L52+(ROW()/1000000),"")
A53: LOAN059 | B53: CUS401 | C53: 45939 | D53: 45944 | E53: Business Loan | F53: 49887.29 | G53: 48147.85 | H53: 10.378 | I53: 90 | J53: Defaulted | K53: 23229.54 | L53: 30 | M53: =IF(J53="Active",L53+(ROW()/1000000),"")
A54: LOAN060 | B54: CUS537 | C54: 45982 | D54: 45986 | E54: Mobile Credit | F54: 272135.11 | G54: 172825.75 | H54: 14.982 | I54: 120 | J54: Active | K54: 73076.54 | L54: 10 | M54: =IF(J54="Active",L54+(ROW()/1000000),"") -> 10.000054
A55: LOAN061 | B55: CUS858 | C55: 45869 | D55: 45871 | E55: Mobile Credit | F55: 22958.9 | G55: 20769.92 | H55: 17.921 | I55: 30 | J55: Defaulted | K55: 4659.61 | L55: 0 | M55: =IF(J55="Active",L55+(ROW()/1000000),"")
A56: LOAN062 | B56: CUS380 | C56: 45618 | D56: 45619 | E56: Business Loan | F56: 423718.2 | G56: 290092.86 | H56: 17.191 | I56: 180 | J56: Defaulted | K56: 251224.29 | L56: 60 | M56: =IF(J56="Active",L56+(ROW()/1000000),"")
A57: LOAN063 | B57: CUS377 | C57: 45842 | D57: 45846 | E57: Mobile Credit | F57: 214612.26 | G57: 149037.17 | H57: 14.044 | I57: 120 | J57: Paid | K57: 0 | L57: 0 | M57: =IF(J57="Active",L57+(ROW()/1000000),"")
A58: LOAN064 | B58: CUS529 | C58: 45384 | D58: 45387 | E58: Salary Advance | F58: 22197.79 | G58: 17387.37 | H58: 14.644 | I58: 60 | J58: Active | K58: 14433.93 | L58: 0 | M58: =IF(J58="Active",L58+(ROW()/1000000),"") -> 5.8e-05
A59: LOAN065 | B59: CUS357 | C59: 45887 | D59: 45892 | E59: Business Loan | F59: 59011 | G59: 52015.82 | H59: 10.606 | I59: 60 | J59: Paid | K59: 0 | L59: 0 | M59: =IF(J59="Active",L59+(ROW()/1000000),"")
A60: LOAN066 | B60: CUS207 | C60: 45472 | D60: 45477 | E60: Mobile Credit | F60: 348053.04 | G60: 200167.92 | H60: 10.179 | I60: 90 | J60: Paid | K60: 0 | L60: 0 | M60: =IF(J60="Active",L60+(ROW()/1000000),"")
A61: LOAN067 | B61: CUS857 | C61: 45803 | D61: 45804 | E61: Business Loan | F61: 458946.31 | G61: 410589.63 | H61: 15.486 | I61: 90 | J61: Active | K61: 320204.3 | L61: 30 | M61: =IF(J61="Active",L61+(ROW()/1000000),"") -> 30.000061
A62: LOAN068 | B62: CUS106 | C62: 45581 | E62: Business Loan | F62: 67152.27 | G62: 0 | H62: 9.213 | I62: 120 | J62: Rejected | K62: 0 | L62: 0 | M62: =IF(J62="Active",L62+(ROW()/1000000),"")
A63: LOAN069 | B63: CUS718 | C63: 45348 | D63: 45353 | E63: Mobile Credit | F63: 106739.45 | G63: 81026.17 | H63: 12.771 | I63: 30 | J63: Active | K63: 69884.93 | L63: 0 | M63: =IF(J63="Active",L63+(ROW()/1000000),"") -> 6.3e-05
A64: LOAN070 | B64: CUS046 | C64: 45681 | D64: 45684 | E64: Business Loan | F64: 391681.77 | G64: 365800.25 | H64: 9.286 | I64: 90 | J64: Active | K64: 94806.09 | L64: 5 | M64: =IF(J64="Active",L64+(ROW()/1000000),"") -> 5.000064
A65: LOAN071 | B65: CUS697 | C65: 45717 | D65: 45722 | E65: Mobile Credit | F65: 94821.65 | G65: 94811.45 | H65: 14.97 | I65: 120 | J65: Active | K65: 36770.28 | L65: 3 | M65: =IF(J65="Active",L65+(ROW()/1000000),"") -> 3.000065
A66: LOAN072 | B66: CUS285 | C66: 45367 | D66: 45371 | E66: Mobile Credit | F66: 204713.38 | G66: 129103.04 | H66: 15.927 | I66: 90 | J66: Defaulted | K66: 83603.61 | L66: 30 | M66: =IF(J66="Active",L66+(ROW()/1000000),"")
A67: LOAN073 | B67: CUS155 | C67: 45388 | D67: 45390 | E67: Salary Advance | F67: 361941.3 | G67: 341720.98 | H67: 14.038 | I67: 60 | J67: Paid | K67: 0 | L67: 0 | M67: =IF(J67="Active",L67+(ROW()/1000000),"")
A68: LOAN074 | B68: CUS970 | C68: 45651 | D68: 45656 | E68: Business Loan | F68: 240049.58 | G68: 202200.81 | H68: 7.479 | I68: 90 | J68: Active | K68: 79504.16 | L68: 60 | M68: =IF(J68="Active",L68+(ROW()/1000000),"") -> 60.000068
A69: LOAN075 | B69: CUS549 | C69: 45664 | D69: 45665 | E69: Business Loan | F69: 197287.69 | G69: 164750.06 | H69: 10.16 | I69: 120 | J69: Active | K69: 130111.67 | L69: 3 | M69: =IF(J69="Active",L69+(ROW()/1000000),"") -> 3.000069
A70: LOAN076 | B70: CUS158 | C70: 45464 | D70: 45469 | E70: Business Loan | F70: 22588.08 | G70: 15671.62 | H70: 15.83 | I70: 60 | J70: Paid | K70: 0 | L70: 0 | M70: =IF(J70="Active",L70+(ROW()/1000000),"")
A71: LOAN077 | B71: CUS047 | C71: 45707 | D71: 45711 | E71: Business Loan | F71: 480793.19 | G71: 479367.94 | H71: 14.216 | I71: 180 | J71: Active | K71: 31304.58 | L71: 5 | M71: =IF(J71="Active",L71+(ROW()/1000000),"") -> 5.000071
A72: LOAN078 | B72: CUS139 | C72: 45776 | D72: 45778 | E72: Mobile Credit | F72: 423592.85 | G72: 264452.7 | H72: 12.572 | I72: 30 | J72: Paid | K72: 0 | L72: 0 | M72: =IF(J72="Active",L72+(ROW()/1000000),"")
A73: LOAN079 | B73: CUS771 | C73: 45675 | D73: 45680 | E73: Mobile Credit | F73: 283392.38 | G73: 270968.46 | H73: 9.408 | I73: 90 | J73: Paid | K73: 0 | L73: 0 | M73: =IF(J73="Active",L73+(ROW()/1000000),"")
A74: LOAN080 | B74: CUS973 | C74: 45658 | D74: 45662 | E74: Mobile Credit | F74: 123731.35 | G74: 88688.85 | H74: 12.784 | I74: 60 | J74: Paid | K74: 0 | L74: 0 | M74: =IF(J74="Active",L74+(ROW()/1000000),"")
... A85: LOAN091 | B85: CUS175 | C85: 45586 | D85: 45587 | E85: Mobile Credit | F85: 16067.86 | G85: 10510.77 | H85: 7.3 | I85: 60 | J85: Active | K85: 7847.32 | L85: 0 | M85: =IF(J85="Active",L85+(ROW()/1000000),"") -> 8.5e-05
A86: LOAN092 | B86: CUS133 | C86: 45750 | E86: Mobile Credit | F86: 469431.39 | G86: 0 | H86: 12.99 | I86: 60 | J86: Rejected | K86: 0 | L86: 0 | M86: =IF(J86="Active",L86+(ROW()/1000000),"")
A87: LOAN093 | B87: CUS272 | C87: 45970 | D87: 45973 | E87: Business Loan | F87: 169790.85 | G87: 142337.73 | H87: 9.533 | I87: 60 | J87: Active | K87: 79774.18 | L87: 3 | M87: =IF(J87="Active",L87+(ROW()/1000000),"") -> 3.000087
A88: LOAN094 | B88: CUS619 | C88: 45622 | D88: 45625 | E88: Mobile Credit | F88: 62704.23 | G88: 61038.9 | H88: 13.472 | I88: 180 | J88: Paid | K88: 0 | L88: 0 | M88: =IF(J88="Active",L88+(ROW()/1000000),"")
A89: LOAN095 | B89: CUS282 | C89: 45709 | D89: 45709 | E89: Salary Advance | F89: 246655.23 | G89: 177377.88 | H89: 16.55 | I89: 120 | J89: Defaulted | K89: 152483.08 | L89: 60 | M89: =IF(J89="Active",L89+(ROW()/1000000),"")
A90: LOAN096 | B90: CUS594 | C90: 45663 | D90: 45663 | E90: Salary Advance | F90: 191102.15 | G90: 182941.57 | H90: 12.114 | I90: 180 | J90: Active | K90: 100003.98 | L90: 0 | M90: =IF(J90="Active",L90+(ROW()/1000000),"") -> 9e-05
A91: LOAN097 | B91: CUS056 | C91: 45693 | D91: 45693 | E91: Mobile Credit | F91: 448580.85 | G91: 294657.9 | H91: 14.935 | I91: 90 | J91: Active | K91: 48905.62 | L91: 3 | M91: =IF(J91="Active",L91+(ROW()/1000000),"") -> 3.000091
A92: LOAN098 | B92: CUS434 | C92: 45773 | D92: 45778 | E92: Business Loan | F92: 86113.7 | G92: 50030.94 | H92: 9.057 | I92: 60 | J92: Defaulted | K92: 44490.94 | L92: 3 | M92: =IF(J92="Active",L92+(ROW()/1000000),"")
A93: LOAN099 | B93: CUS299 | C93: 45620 | E93: Salary Advance | F93: 335912.86 | G93: 0 | H93: 12.178 | I93: 120 | J93: Rejected | K93: 0 | L93: 0 | M93: =IF(J93="Active",L93+(ROW()/1000000),"")
A94: LOAN100 | B94: CUS886 | C94: 45757 | D94: 45762 | E94: Mobile Credit | F94: 274226.23 | G94: 242295.35 | H94: 7.704 | I94: 120 | J94: Active | K94: 77692.58 | L94: 60 | M94: =IF(J94="Active",L94+(ROW()/1000000),"") -> 60.000094
A95: LOAN101 | B95: CUS171 | C95: 45900 | D95: 45904 | E95: Salary Advance | F95: 87048.16 | G95: 86719.52 | H95: 14.928 | I95: 30 | J95: Active | K95: 70999.88 | L95: 3 | M95: =IF(J95="Active",L95+(ROW()/1000000),"") -> 3.000095
A96: LOAN102 | B96: CUS202 | C96: 45804 | D96: 45806 | E96: Salary Advance | F96: 92417.87 | G96: 57622.79 | H96: 17.938 | I96: 120 | J96: Paid | K96: 0 | L96: 0 | M96: =IF(J96="Active",L96+(ROW()/1000000),"")
A97: LOAN103 | B97: CUS149 | C97: 45788 | D97: 45793 | E97: Salary Advance | F97: 18566.2 | G97: 15064.73 | H97: 14.562 | I97: 90 | J97: Defaulted | K97: 4702.33 | L97: 0 | M97: =IF(J97="Active",L97+(ROW()/1000000),"")
A98: LOAN104 | B98: CUS307 | C98: 45368 | D98: 45369 | E98: Business Loan | F98: 159192.23 | G98: 153779.53 | H98: 15.921 | I98: 120 | J98: Active | K98: 89382.3 | L98: 1 | M98: =IF(J98="Active",L98+(ROW()/1000000),"") -> 1.000098
A99: LOAN105 | B99: CUS454 | C99: 45983 | D99: 45987 | E99: Salary Advance | F99: 263589.02 | G99: 242729.89 | H99: 14.085 | I99: 30 | J99: Active | K99: 60309.75 | L99: 3 | M99: =IF(J99="Active",L99+(ROW()/1000000),"") -> 3.000099
A100: LOAN106 | B100: CUS287 | C100: 45716 | D100: 45717 | E100: Business Loan | F100: 348598.21 | G100: 287985.17 | H100: 8.242 | I100: 60 | J100: Active | K100: 65359.47 | L100: 30 | M100: =IF(J100="Active",L100+(ROW()/1000000),"") -> 30.0001
A101: LOAN107 | B101: CUS880 | C101: 45642 | E101: Salary Advance | F101: 410404.65 | G101: 0 | H101: 16.733 | I101: 60 | J101: Rejected | K101: 0 | L101: 0 | M101: =IF(J101="Active",L101+(ROW()/1000000),"")
A102: LOAN108 | B102: CUS213 | C102: 45826 | D102: 45828 | E102: Salary Advance | F102: 256689.86 | G102: 250137.37 | H102: 7.877 | I102: 180 | J102: Paid | K102: 0 | L102: 0 | M102: =IF(J102="Active",L102+(ROW()/1000000),"")
A103: LOAN109 | B103: CUS023 | C103: 45640 | D103: 45645 | E103: Business Loan | F103: 382410.04 | G103: 310015.08 | H103: 10.975 | I103: 90 | J103: Active | K103: 90267.24 | L103: 60 | M103: =IF(J103="Active",L103+(ROW()/1000000),"") -> 60.000103
A104: LOAN110 | B104: CUS061 | C104: 45812 | D104: 45815 | E104: Salary Advance | F104: 495693.28 | G104: 349668.8 | H104: 14.68 | I104: 60 | J104: Defaulted | K104: 58114.76 | L104: 1 | M104: =IF(J104="Active",L104+(ROW()/1000000),"")
A105: LOAN111 | B105: CUS015 | C105: 45297 | D105: 45297 | E105: Salary Advance | F105: 7216.85 | G105: 5337.7 | H105: 11.793 | I105: 90 | J105: Paid | K105: 0 | L105: 0 | M105: =IF(J105="Active",L105+(ROW()/1000000),"")
A106: LOAN112 | B106: CUS516 | C106: 45597 | D106: 45602 | E106: Salary Advance | F106: 342229.31 | G106: 232136.84 | H106: 15.286 | I106: 60 | J106: Paid | K106: 0 | L106: 0 | M106: =IF(J106="Active",L106+(ROW()/1000000),"")
A107: LOAN113 | B107: CUS761 | C107: 45926 | D107: 45928 | E107: Business Loan | F107: 138094.21 | G107: 91463.34 | H107: 7.455 | I107: 120 | J107: Active | K107: 83115.08 | L107: 15 | M107: =IF(J107="Active",L107+(ROW()/1000000),"") -> 15.000107
A108: LOAN114 | B108: CUS586 | C108: 45431 | D108: 45436 | E108: Business Loan | F108: 419998.23 | G108: 317574.73 | H108: 16.006 | I108: 90 | J108: Defaulted | K108: 16071.88 | L108: 1 | M108: =IF(J108="Active",L108+(ROW()/1000000),"")
A109: LOAN115 | B109: CUS823 | C109: 45942 | D109: 45942 | E109: Business Loan | F109: 354861.24 | G109: 337664.58 | H109: 10.906 | I109: 120 | J109: Defaulted | K109: 258780.58 | L109: 0 | M109: =IF(J109="Active",L109+(ROW()/1000000),"")
A110: LOAN116 | B110: CUS183 | C110: 45961 | D110: 45966 | E110: Business Loan | F110: 489336.05 | G110: 300587.21 | H110: 11.903 | I110: 180 | J110: Paid | K110: 0 | L110: 0 | M110: =IF(J110="Active",L110+(ROW()/1000000),"")
A111: LOAN117 | B111: CUS027 | C111: 45954 | E111: Mobile Credit | F111: 414565.01 | G111: 0 | H111: 15.129 | I111: 180 | J111: Rejected | K111: 0 | L111: 0 | M111: =IF(J111="Active",L111+(ROW()/1000000),"")
A112: LOAN118 | B112: CUS412 | C112: 45601 | D112: 45603 | E112: Mobile Credit | F112: 22524.28 | G112: 14419.38 | H112: 16.255 | I112: 90 | J112: Paid | K112: 0 | L112: 0 | M112: =IF(J112="Active",L112+(ROW()/1000000),"")
...

Sheet Data_Customers
A1: customer_id | B1: first_name | C1: last_name | D1: gender | E1: date_of_birth | F1: phone_number | G1: county_id | H1: customer_type | I1: occupation | J1: income_band | K1: registration_date | L1: kyc_status | M1: customer_status
A2: CUS001 | B2: Brian | C2: Mwangi | D2: Male | E2: 35167 | F2: 254700000001 | G2: 1 | H2: Individual | I2: Software Developer | J2: 100K-250K | K2: 45306 | L2: Verified | M2: Active
A3: CUS002 | B3: Wanjiku | C3: Kamau | D3: Female | E3: 34566 | F3: 254700000002 | G3: 5 | H3: Individual | I3: Business Owner | J3: 50K-100K | K3: 45332 | L3: Verified | M3: Active
A4: CUS003 | B4: Kevin | C4: Otieno | D4: Male | E4: 35800 | F4: 254700000003 | G4: 3 | H4: Individual | I4: Teacher | J4: 30K-50K | K4: 45355 | L4: Verified | M4: Active
A5: CUS004 | B5: Amina | C5: Hassan | D5: Female | E5: 33560 | F5: 254700000004 | G5: 2 | H5: Individual | I5: Trader | J5: 50K-100K | K5: 45319 | L5: Verified | M5: Active
A6: CUS005 | B6: David | C6: Kiptoo | D6: Male | E6: 32354 | F6: 254700000005 | G6: 7 | H6: Individual | I6: Farmer | J6: 30K-50K | K6: 45394 | L6: Verified | M6: Active
A7: CUS006 | B7: Faith | C7: Njeri | D7: Female | E7: 36230 | F7: 254700000006 | G7: 6 | H7: Individual | I7: Freelancer | J7: 50K-100K | K7: 45433 | L7: Verified | M7: Active
A8: CUS007 | B8: Samuel | C8: Omondi | D8: Male | E8: 31292 | F8: 254700000007 | G8: 4 | H8: Individual | I8: Business Owner | J8: 100K-250K | K8: 45336 | L8: Verified | M8: Active
A9: CUS008 | B9: Mercy | C9: Achieng | D9: Female | E9: 35604 | F9: 254700000008 | G9: 8 | H9: Individual | I9: Retail Worker | J9: 30K-50K | K9: 45444 | L9: Verified | M9: Active
A10: CUS009 | B10: John | C10: Kamau | D10: Male | E10: 33226 | F10: 254700000009 | G10: 11 | H10: Individual | I10: Engineer | J10: 100K-250K | K10: 45300 | L10: Verified | M10: Active
A11: CUS010 | B11: Grace | C11: Muthoni | D11: Female | E11: 34834 | F11: 254700000010 | G11: 14 | H11: Individual | I11: Entrepreneur | J11: 50K-100K | K11: 45366 | L11: Verified | M11: Active
A12: CUS011 | B12: John | C12: Omondi | D12: Male | E12: 28149 | F12: 254723756669 | G12: 11 | H12: Individual | I12: Driver | J12: 100K-250K | K12: 45208 | L12: Verified | M12: Active
A13: CUS012 | B13: Joseph | C13: Mwangi | D13: Male | E13: 27492 | F13: 254797226012 | G13: 12 | H13: SME | I13: Trader | J13: 100K-250K | K13: 45444 | L13: Verified | M13: Active
... A1001: CUS1000 | B1001: James | C1001: Maina | D1001: Female | E1001: 37061 | F1001: 254794694930 | G1001: 11 | H1001: Individual | I1001: Software Developer | J1001: 250K+ | K1001: 45299 | L1001: Pending | M1001: Active

Sheet Data_Fraud
A1: fraud_event_id | B1: transaction_id | C1: detected_at | D1: fraud_type | E1: risk_score | F1: investigation_status | G1: confirmed_fraud
A2: FRD0003 | B2: TXN2383 | C2: 45475.333 | D2: Velocity anomaly | E2: 0.903 | F2: Confirmed | G2: =FALSE() -> FALSE
A3: FRD0004 | B3: TXN1087 | C3: 45687.708 | D3: Velocity anomaly | E3: 0.821 | F3: Closed | G3: =FALSE() -> FALSE
A4: FRD0005 | B4: TXN1417 | C4: 45439.208 | D4: New beneficiary risk | E4: 0.636 | F4: Investigating | G4: =FALSE() -> FALSE
A5: FRD0006 | B5: TXN0355 | C5: 45855.583 | D5: New beneficiary risk | E5: 0.727 | F5: Confirmed | G5: =FALSE() -> FALSE
A6: FRD0007 | B6: TXN2569 | C6: 45361.333 | D6: Multiple failed attempts | E6: 0.694 | F6: Confirmed | G6: =FALSE() -> FALSE
A7: FRD0008 | B7: TXN1808 | C7: 45599.583 | D7: New beneficiary risk | E7: 0.859 | F7: Investigating | G7: =FALSE() -> FALSE
A8: FRD0009 | B8: TXN2700 | C8: 45371 | D8: Velocity anomaly | E8: 0.828 | F8: New | G8: =FALSE() -> FALSE
A9: FRD0010 | B9: TXN1798 | C9: 45475.625 | D9: New beneficiary risk | E9: 0.804 | F9: Confirmed | G9: =FALSE() -> FALSE
A10: FRD0011 | B10: TXN1679 | C10: 45975.708 | D10: New beneficiary risk | E10: 0.978 | F10: Confirmed | G10: =FALSE() -> FALSE
A11: FRD0012 | B11: TXN2992 | C11: 45470 | D11: Multiple failed attempts | E11: 0.905 | F11: New | G11: =FALSE() -> FALSE
A12: FRD0013 | B12: TXN1329 | C12: 45773.708 | D12: Multiple failed attempts | E12: 0.859 | F12: Confirmed | G12: =FALSE() -> FALSE
A13: FRD0014 | B13: TXN0286 | C13: 45706.25 | D13: Multiple failed attempts | E13: 0.668 | F13: Confirmed | G13: =FALSE() -> FALSE
... A23: FRD0024 | B23: TXN3013 | C23: 45907.458 | D23: New beneficiary risk | E23: 0.868 | F23: Confirmed | G23: =FALSE() -> FALSE
A24: FRD0025 | B24: TXN0802 | C24: 45616.125 | D24: New beneficiary risk | E24: 0.977 | F24: Investigating | G24: =TRUE() -> TRUE
A25: FRD0026 | B25: TXN0737 | C25: 45454.583 | D25: Unusual transaction amount | E25: 0.967 | F25: New | G25: =TRUE() -> TRUE
A26: FRD0027 | B26: TXN0206 | C26: 45353.167 | D26: Unusual transaction amount | E26: 0.631 | F26: Closed | G26: =FALSE() -> FALSE
A27: FRD0028 | B27: TXN0211 | C27: 45324.958 | D27: Multiple failed attempts | E27: 0.834 | F27: Confirmed | G27: =FALSE() -> FALSE
A28: FRD0029 | B28: TXN1291 | C28: 45632.458 | D28: New beneficiary risk | E28: 0.98 | F28: Confirmed | G28: =TRUE() -> TRUE
A29: FRD0030 | B29: TXN0888 | C29: 45445.708 | D29: Velocity anomaly | E29: 0.868 | F29: Investigating | G29: =FALSE() -> FALSE
A30: FRD0031 | B30: TXN0280 | C30: 45484.167 | D30: Unusual transaction amount | E30: 0.945 | F30: Investigating | G30: =FALSE() -> FALSE
A31: FRD0032 | B31: TXN2976 | C31: 45560.792 | D31: Velocity anomaly | E31: 0.826 | F31: Closed | G31: =FALSE() -> FALSE
A32: FRD0033 | B32: TXN2627 | C32: 45302.667 | D32: Multiple failed attempts | E32: 0.829 | F32: Confirmed | G32: =FALSE() -> FALSE
A33: FRD0034 | B33: TXN2037 | C33: 45503.167 | D33: New beneficiary risk | E33: 0.834 | F33: Closed | G33: =FALSE() -> FALSE
A34: FRD0035 | B34: TXN1372 | C34: 45729.167 | D34: New beneficiary risk | E34: 0.799 | F34: New | G34: =FALSE() -> FALSE
A35: FRD0036 | B35: TXN0777 | C35: 45769.042 | D35: Velocity anomaly | E35: 0.951 | F35: Closed | G35: =FALSE() -> FALSE
A36: FRD0037 | B36: TXN2500 | C36: 45829.333 | D36: Multiple failed attempts | E36: 0.753 | F36: New | G36: =FALSE() -> FALSE
A37: FRD0038 | B37: TXN1555 | C37: 45700 | D37: Multiple failed attempts | E37: 0.835 | F37: Confirmed | G37: =FALSE() -> FALSE
A38: FRD0039 | B38: TXN0224 | C38: 45718.167 | D38: New beneficiary risk | E38: 0.805 | F38: Closed | G38: =FALSE() -> FALSE
A39: FRD0040 | B39: TXN1359 | C39: 45806.708 | D39: New beneficiary risk | E39: 0.758 | F39: Investigating | G39: =FALSE() -> FALSE
A40: FRD0041 | B40: TXN1098 | C40: 45599.5 | D40: Velocity anomaly | E40: 0.985 | F40: New | G40: =TRUE() -> TRUE
A41: FRD0042 | B41: TXN1148 | C41: 45435.875 | D41: Unusual transaction amount | E41: 0.807 | F41: Investigating | G41: =FALSE() -> FALSE
A42: FRD0043 | B42: TXN2400 | C42: 45543.875 | D42: Unusual transaction amount | E42: 0.779 | F42: New | G42: =FALSE() -> FALSE
A43: FRD0044 | B43: TXN0587 | C43: 45433.042 | D43: Velocity anomaly | E43: 0.867 | F43: New | G43: =FALSE() -> FALSE
A44: FRD0045 | B44: TXN0395 | C44: 45433.833 | D44: Multiple failed attempts | E44: 0.733 | F44: New | G44: =FALSE() -> FALSE
A45: FRD0046 | B45: TXN2088 | C45: 45577.042 | D45: Multiple failed attempts | E45: 0.682 | F45: Closed | G45: =FALSE() -> FALSE
A46: FRD0047 | B46: TXN2929 | C46: 45689.875 | D46: Multiple failed attempts | E46: 0.928 | F46: Investigating | G46: =FALSE() -> FALSE
A47: FRD0048 | B47: TXN006 | C47: 45842.583 | D47: New beneficiary risk | E47: 0.791 | F47: Confirmed | G47: =FALSE() -> FALSE
A48: FRD0049 | B48: TXN2517 | C48: 45347.042 | D48: Velocity anomaly | E48: 0.745 | F48: Investigating | G48: =FALSE() -> FALSE
A49: FRD0050 | B49: TXN2972 | C49: 45733 | D49: New beneficiary risk | E49: 0.662 | F49: Investigating | G49: =FALSE() -> FALSE
A50: FRD0051 | B50: TXN1902 | C50: 45813.958 | D50: Multiple failed attempts | E50: 0.712 | F50: Investigating | G50: =FALSE() -> FALSE
A51: FRD0052 | B51: TXN1916 | C51: 45554.708 | D51: Multiple failed attempts | E51: 0.663 | F51: Confirmed | G51: =FALSE() -> FALSE
A52: FRD0053 | B52: TXN2605 | C52: 45516.083 | D52: Unusual transaction amount | E52: 0.706 | F52: Investigating | G52: =FALSE() -> FALSE
... A60: FRD0061 | B60: TXN1352 | C60: 45770 | D60: New beneficiary risk | E60: 0.643 | F60: Confirmed | G60: =FALSE() -> FALSE
A61: FRD0062 | B61: TXN1873 | C61: 45802.792 | D61: Velocity anomaly | E61: 0.952 | F61: Closed | G61: =TRUE() -> TRUE
A62: FRD0063 | B62: TXN1408 | C62: 45599.958 | D62: New beneficiary risk | E62: 0.878 | F62: Closed | G62: =FALSE() -> FALSE
A63: FRD0064 | B63: TXN1795 | C63: 45363.125 | D63: Velocity anomaly | E63: 0.855 | F63: New | G63: =FALSE() -> FALSE
A64: FRD0065 | B64: TXN2841 | C64: 45717.667 | D64: New beneficiary risk | E64: 0.746 | F64: Investigating | G64: =FALSE() -> FALSE
A65: FRD0066 | B65: TXN0170 | C65: 45425.375 | D65: Velocity anomaly | E65: 0.646 | F65: Confirmed | G65: =FALSE() -> FALSE
A66: FRD0067 | B66: TXN1300 | C66: 45907.958 | D66: New beneficiary risk | E66: 0.914 | F66: Investigating | G66: =FALSE() -> FALSE
A67: FRD0068 | B67: TXN1146 | C67: 45729.667 | D67: Multiple failed attempts | E67: 0.823 | F67: Closed | G67: =FALSE() -> FALSE
A68: FRD0069 | B68: TXN2904 | C68: 45393 | D68: Unusual transaction amount | E68: 0.8 | F68: Investigating | G68: =FALSE() -> FALSE
A69: FRD0070 | B69: TXN2273 | C69: 45987.458 | D69: New beneficiary risk | E69: 0.934 | F69: Investigating | G69: =FALSE() -> FALSE
A70: FRD0071 | B70: TXN2847 | C70: 45776.458 | D70: Unusual transaction amount | E70: 0.866 | F70: Investigating | G70: =FALSE() -> FALSE
A71: FRD0072 | B71: TXN0291 | C71: 45912.167 | D71: New beneficiary risk | E71: 0.791 | F71: Closed | G71: =FALSE() -> FALSE
A72: FRD0073 | B72: TXN0028 | C72: 45469.292 | D72: New beneficiary risk | E72: 0.672 | F72: Investigating | G72: =FALSE() -> FALSE
A73: FRD0074 | B73: TXN2115 | C73: 45852 | D73: New beneficiary risk | E73: 0.962 | F73: Investigating | G73: =FALSE() -> FALSE
... A78: FRD0079 | B78: TXN1366 | C78: 45319.208 | D78: Unusual transaction amount | E78: 0.674 | F78: New | G78: =FALSE() -> FALSE
A79: FRD0080 | B79: TXN2084 | C79: 45774 | D79: Unusual transaction amount | E79: 0.936 | F79: New | G79: =TRUE() -> TRUE
A80: FRD0081 | B80: TXN0733 | C80: 45422.042 | D80: Multiple failed attempts | E80: 0.94 | F80: Investigating | G80: =TRUE() -> TRUE
A81: FRD0082 | B81: TXN2220 | C81: 45892.292 | D81: Multiple failed attempts | E81: 0.665 | F81: Confirmed | G81: =FALSE() -> FALSE
A82: FRD0083 | B82: TXN0202 | C82: 45833.75 | D82: Unusual transaction amount | E82: 0.984 | F82: Closed | G82: =FALSE() -> FALSE
A83: FRD0084 | B83: TXN1831 | C83: 45411 | D83: Unusual transaction amount | E83: 0.628 | F83: Closed | G83: =FALSE() -> FALSE
A84: FRD0085 | B84: TXN2198 | C84: 45477.333 | D84: New beneficiary risk | E84: 0.783 | F84: Closed | G84: =FALSE() -> FALSE
A85: FRD0086 | B85: TXN2515 | C85: 45394.125 | D85: New beneficiary risk | E85: 0.95 | F85: Investigating | G85: =FALSE() -> FALSE
A86: FRD0087 | B86: TXN1716 | C86: 45623.042 | D86: New beneficiary risk | E86: 0.908 | F86: Closed | G86: =FALSE() -> FALSE
A87: FRD0088 | B87: TXN1760 | C87: 45331.208 | D87: New beneficiary risk | E87: 0.78 | F87: Investigating | G87: =FALSE() -> FALSE
A88: FRD0089 | B88: TXN0082 | C88: 45536.458 | D88: Unusual transaction amount | E88: 0.647 | F88: Investigating | G88: =FALSE() -> FALSE
A89: FRD0090 | B89: TXN1394 | C89: 45307.5 | D89: Velocity anomaly | E89: 0.869 | F89: Investigating | G89: =FALSE() -> FALSE
A90: FRD0091 | B90: TXN0250 | C90: 45999.917 | D90: Multiple failed attempts | E90: 0.889 | F90: Investigating | G90: =FALSE() -> FALSE
A91: FRD0092 | B91: TXN1128 | C91: 45382.875 | D91: New beneficiary risk | E91: 0.929 | F91: Closed | G91: =FALSE() -> FALSE
A92: FRD0093 | B92: TXN1286 | C92: 45733.375 | D92: New beneficiary risk | E92: 0.848 | F92: Confirmed | G92: =FALSE() -> FALSE
... A115: FRD0116 | B115: TXN1324 | C115: 45756.042 | D115: Unusual transaction amount | E115: 0.889 | F115: Confirmed | G115: =FALSE() -> FALSE
A116: FRD0117 | B116: TXN1839 | C116: 45547.292 | D116: New beneficiary risk | E116: 0.936 | F116: New | G116: =TRUE() -> TRUE
A117: FRD0118 | B117: TXN0789 | C117: 45703.042 | D117: Multiple failed attempts | E117: 0.765 | F117: Closed | G117: =FALSE() -> FALSE
A118: FRD0119 | B118: TXN2315 | C118: 45790.083 | D118: Velocity anomaly | E118: 0.908 | F118: Confirmed | G118: =FALSE() -> FALSE
A119: FRD0120 | B119: TXN0324 | C119: 45934.042 | D119: Velocity anomaly | E119: 0.825 | F119: Confirmed | G119: =FALSE() -> FALSE
A120: FRD0121 | B120: TXN2655 | C120: 45784.583 | D120: Multiple failed attempts | E120: 0.664 | F120: Confirmed | G120: =FALSE() -> FALSE
A121: FRD0122 | B121: TXN2980 | C121: 45904.792 | D121: Unusual transaction amount | E121: 0.931 | F121: Confirmed | G121: =FALSE() -> FALSE
A122: FRD0123 | B122: TXN2071 | C122: 45736.792 | D122: New beneficiary risk | E122: 0.717 | F122: New | G122: =FALSE() -> FALSE
A123: FRD0124 | B123: TXN1473 | C123: 45685.5 | D123: Unusual transaction amount | E123: 0.838 | F123: New | G123: =FALSE() -> FALSE
A124: FRD0125 | B124: TXN2278 | C124: 45483.708 | D124: Velocity anomaly | E124: 0.92 | F124: New | G124: =FALSE() -> FALSE
A125: FRD0126 | B125: TXN1970 | C125: 45612.667 | D125: New beneficiary risk | E125: 0.875 | F125: Closed | G125: =FALSE() -> FALSE
A126: FRD0127 | B126: TXN2303 | C126: 45535 | D126: New beneficiary risk | E126: 0.686 | F126: Closed | G126: =FALSE() -> FALSE
A127: FRD0128 | B127: TXN0812 | C127: 45999.5 | D127: Velocity anomaly | E127: 0.687 | F127: New | G127: =FALSE() -> FALSE
A128: FRD0129 | B128: TXN2369 | C128: 45429.667 | D128: New beneficiary risk | E128: 0.974 | F128: New | G128: =FALSE() -> FALSE
... A145: FRD0146 | B145: TXN2815 | C145: 45945.208 | D145: Unusual transaction amount | E145: 0.693 | F145: Closed | G145: =FALSE() -> FALSE
A146: FRD0147 | B146: TXN2412 | C146: 45310.333 | D146: Unusual transaction amount | E146: 0.922 | F146: New | G146: =TRUE() -> TRUE
A147: FRD0148 | B147: TXN1013 | C147: 45949.75 | D147: Velocity anomaly | E147: 0.92 | F147: New | G147: =FALSE() -> FALSE
A148: FRD0149 | B148: TXN2976 | C148: 45371.75 | D148: Velocity anomaly | E148: 0.848 | F148: Confirmed | G148: =FALSE() -> FALSE
A149: FRD0150 | B149: TXN0604 | C149: 45564.375 | D149: Velocity anomaly | E149: 0.899 | F149: Confirmed | G149: =FALSE() -> FALSE
A150: FRD0151 | B150: TXN1184 | C150: 45622.5 | D150: Unusual transaction amount | E150: 0.877 | F150: Closed | G150: =FALSE() -> FALSE
A151: FRD0152 | B151: TXN2349 | C151: 45393.458 | D151: Velocity anomaly | E151: 0.766 | F151: Investigating | G151: =FALSE() -> FALSE

Sheet Data_Fees
A1: fee_id | B1: transaction_id | C1: fee_type | D1: fee_amount | E1: fee_date
A2: FEE0001 | B2: TXN001 | C2: Withdrawal Fee | D2: 25 | E2: 45299
A3: FEE0002 | B3: TXN002 | C3: Transaction Fee | D3: 5.74 | E3: 45306
A4: FEE0003 | B4: TXN003 | C4: Transfer Fee | D4: 6.11 | E4: 45313
A5: FEE0004 | B5: TXN004 | C5: Transfer Fee | D5: 6.48 | E5: 45320
A6: FEE0005 | B6: TXN005 | C6: Withdrawal Fee | D6: 6.85 | E6: 45327
A7: FEE0006 | B7: TXN006 | C7: Transaction Fee | D7: 7.22 | E7: 45334
A8: FEE0007 | B8: TXN007 | C8: Merchant Fee | D8: 7.59 | E8: 45341
A9: FEE0008 | B9: TXN008 | C9: Transaction Fee | D9: 7.96 | E9: 45348
A10: FEE0009 | B10: TXN009 | C10: Withdrawal Fee | D10: 8.33 | E10: 45355
A11: FEE0010 | B11: TXN010 | C11: Withdrawal Fee | D11: 8.7 | E11: 45362
A12: FEE0011 | B12: TXN011 | C12: Merchant Fee | D12: 9.07 | E12: 45369
A13: FEE0012 | B13: TXN012 | C13: Bill Payment Fee | D13: 9.44 | E13: 45376
... A3016: FEE3015 | B3016: TXN3015 | C3016: Withdrawal Fee | D3016: 120.55 | E3016: 45957
